intentionally_blank/__init__.py
intentionally_blank/api.py
intentionally_blank/cli.py
intentionally_blank/extension.py
intentionally_blank/formatter.py
intentionally_blank/text.py
intentionally_blank/version.py
intentionally_blank/ext/__init__.py
intentionally_blank/ext/formatters/__init__.py
intentionally_blank/ext/formatters/empty/__init__.py
intentionally_blank/ext/formatters/empty/formatter.py
intentionally_blank/ext/formatters/eof_newline/__init__.py
intentionally_blank/ext/formatters/eof_newline/formatter.py
intentionally_blank/ext/formatters/identity/__init__.py
intentionally_blank/ext/formatters/identity/formatter.py
intentionally_blank/ext/formatters/leading/__init__.py
intentionally_blank/ext/formatters/leading/formatter.py
intentionally_blank/ext/formatters/python_leading/__init__.py
intentionally_blank/ext/formatters/python_leading/formatter.py
intentionally_blank/ext/formatters/remove_trailing/__init__.py
intentionally_blank/ext/formatters/remove_trailing/formatter.py
intentionally_blank/ext/formatters/remove_trailing_lines/__init__.py
intentionally_blank/ext/formatters/remove_trailing_lines/formatter.py
intentionally_blank/ext/formatters/visible/__init__.py
intentionally_blank/ext/formatters/visible/formatter.py
intentionally_blank-1.4.0.dist-info/LICENSE.txt
intentionally_blank-1.4.0.dist-info/METADATA
intentionally_blank-1.4.0.dist-info/WHEEL
intentionally_blank-1.4.0.dist-info/entry_points.txt
intentionally_blank-1.4.0.dist-info/top_level.txt
intentionally_blank-1.4.0.dist-info/zip-safe
intentionally_blank-1.4.0.dist-info/RECORD
