Metadata-Version: 2.1
Name: intentionally-blank
Version: 1.4.0
Summary: A tool for indentation in text files
Home-page: https://github.com/sixty-north/intentionally-blank
Author: Sixty North AS
Author-email: systems+intentionally_blank@sixty-north.com
License: MIT License
Keywords: whitespace
Classifier: Development Status :: 5 - Production/Stable
Classifier: Environment :: Console
Classifier: Intended Audience :: Information Technology
Classifier: License :: OSI Approved :: MIT License
Classifier: Programming Language :: Python :: 3 :: Only
Classifier: Programming Language :: Python :: 3.7
Classifier: Programming Language :: Python :: 3.8
Classifier: Programming Language :: Python :: 3.9
Classifier: Programming Language :: Python :: 3.10
License-File: LICENSE.txt
Requires-Dist: stevedore
Requires-Dist: click
Requires-Dist: exit-codes
Requires-Dist: asq
Requires-Dist: more-itertools
Requires-Dist: les-iterables (>=1.0.0)
Provides-Extra: dev
Requires-Dist: black ; extra == 'dev'
Requires-Dist: bumpversion ; extra == 'dev'
Requires-Dist: twine ; extra == 'dev'
Requires-Dist: build ; extra == 'dev'
Provides-Extra: doc
Requires-Dist: sphinx ; extra == 'doc'
Requires-Dist: sphinx-rtd-theme ; extra == 'doc'
Requires-Dist: better-apidoc ; extra == 'doc'
Provides-Extra: test
Requires-Dist: pytest ; extra == 'test'
Requires-Dist: hypothesis ; extra == 'test'
Requires-Dist: tox ; extra == 'test'
